qscache/gen_data.py
qscache/qscache.py
qscache/cfg/casper.cfg
qscache/cfg/derecho.cfg
qscache/cfg/gust.cfg
qscache/cfg/site.cfg.example
qstat_cache-3.0.1.dist-info/licenses/LICENSE
qstat_cache-3.0.1.dist-info/METADATA
qstat_cache-3.0.1.dist-info/WHEEL
qstat_cache-3.0.1.dist-info/entry_points.txt
qstat_cache-3.0.1.dist-info/top_level.txt
qstat_cache-3.0.1.dist-info/RECORD
