Metadata-Version: 2.4
Name: qstat-cache
Version: 3.0.1
Summary: A caching qstat that reduces load on the PBS server
Author-email: Brian Vanderwende <vanderwb@ucar.edu>
License-Expression: MIT
Project-URL: homepage, https://github.com/NCAR/qstat-cache
Project-URL: issues, https://github.com/NCAR/qstat-cache/issues
Classifier: Programming Language :: Python :: 3
Classifier: Operating System :: OS Independent
Classifier: Topic :: System :: Distributed Computing
Requires-Python: >=3.6
License-File: LICENSE
Dynamic: license-file
